incursions/__init__.py
incursions/admin.py
incursions/app_settings.py
incursions/apps.py
incursions/auth_hooks.py
incursions/everef.py
incursions/helpers.py
incursions/providers.py
incursions/signals.py
incursions/static_data.py
incursions/tasks.py
incursions/urls.py
incursions/views.py
incursions/api/__init__.py
incursions/api/announcements.py
incursions/api/auth.py
incursions/api/badges.py
incursions/api/bans.py
incursions/api/categories.py
incursions/api/fittings.py
incursions/api/fleets.py
incursions/api/history.py
incursions/api/implants.py
incursions/api/modules.py
incursions/api/notes.py
incursions/api/pilot.py
incursions/api/schema.py
incursions/api/search.py
incursions/api/skillplans.py
incursions/api/skills.py
incursions/api/sse.py
incursions/api/statistics.py
incursions/api/waitlist.py
incursions/api/window.py
incursions/api/helpers/fittings.py
incursions/api/helpers/sse.py
incursions/cogs/incursions.py
incursions/data.everef.net/readme.md
incursions/data.everef.net/incursions/history/backfills/eve-incursions-de-2023-10-12.json.xz
incursions/fixtures/Incursion.json.xz
incursions/fixtures/IncursionInfluence.json.xz
incursions/fixtures/waitlist_badges.json
incursions/fixtures/waitlist_category.json
incursions/fixtures/waitlist_category_rule.json
incursions/fixtures/waitlist_roles.json
incursions/locale/da_DK/LC_MESSAGES/django.mo
incursions/locale/da_DK/LC_MESSAGES/django.po
incursions/locale/de/LC_MESSAGES/django.mo
incursions/locale/de/LC_MESSAGES/django.po
incursions/locale/en/LC_MESSAGES/django.mo
incursions/locale/en/LC_MESSAGES/django.po
incursions/locale/es/LC_MESSAGES/django.mo
incursions/locale/es/LC_MESSAGES/django.po
incursions/locale/fr_FR/LC_MESSAGES/django.mo
incursions/locale/fr_FR/LC_MESSAGES/django.po
incursions/locale/it_IT/LC_MESSAGES/django.mo
incursions/locale/it_IT/LC_MESSAGES/django.po
incursions/locale/ja/LC_MESSAGES/django.mo
incursions/locale/ja/LC_MESSAGES/django.po
incursions/locale/ko_KR/LC_MESSAGES/django.mo
aa_incursions-1.0.23b0.dist-info/licenses/LICENSE
aa_incursions-1.0.23b0.dist-info/WHEEL
aa_incursions-1.0.23b0.dist-info/METADATA
aa_incursions-1.0.23b0.dist-info/RECORD
