Metadata-Version: 2.4
Name: aa-incursions
Version: 1.0.23b0
Summary: AllianceAuth Incursion Tools
Keywords: allianceauth,eveonline
Author-email: Joel Falknau <joel.falknau@gmail.com>
Requires-Python: >=3.10
Classifier: Environment :: Web Environment
Classifier: Framework :: Celery
Classifier: Framework :: Django
Classifier: Framework :: Django :: 4.2
Classifier: Framework :: Django :: 5.2
Classifier: Intended Audience :: Developers
Classifier: License :: OSI Approved :: MIT License
Classifier: Operating System :: OS Independent
Classifier: Programming Language :: Python
Classifier: Programming Language :: Python :: 3 :: Only
Classifier: Programming Language :: Python :: 3.10
Classifier: Programming Language :: Python :: 3.11
Classifier: Programming Language :: Python :: 3.12
Classifier: Programming Language :: Python :: 3.13
Classifier: Programming Language :: Python :: Implementation :: CPython
Classifier: Topic :: Internet :: WWW/HTTP
Classifier: Topic :: Internet :: WWW/HTTP :: Dynamic Content
License-File: LICENSE
Requires-Dist: aa-routing
Requires-Dist: allianceauth>=4.6.4,<6
Requires-Dist: allianceauth-corptools>=2.10
Requires-Dist: allianceauth-discordbot
Requires-Dist: audioop-lts; python_version>='3.13'
Requires-Dist: django-esi>=7.0.1
Requires-Dist: django-solo>=2,<3
Requires-Dist: py-cord>=2,<3
Requires-Dist: pybase62
Requires-Dist: pynacl
Project-URL: Homepage, https://gitlab.com/tactical-supremacy/aa-incursions
Project-URL: Source, https://gitlab.com/tactical-supremacy/aa-incursions
Project-URL: Tracker, https://gitlab.com/tactical-supremacy/aa-incursions/-/issues
